[{"date":1780214400,"icon":"🌦","temp":28.16,"min":27.59,"max":28.2,"feelsLike":32.02,"pressure":1014,"humidity":77,"windSpeed":6.23,"windDirection":166,"clouds":93,"windGust":6.65,"sunrise":1780194665,"sunset":1780238263},{"date":1780300800,"icon":"🌦","temp":27.99,"min":26.53,"max":28.05,"feelsLike":31.62,"pressure":1014,"humidity":77,"windSpeed":5.92,"windDirection":142,"clouds":100,"windGust":6.54,"sunrise":1780281074,"sunset":1780324672},{"date":1780387200,"icon":"🌦","temp":28.09,"min":26.77,"max":28.2,"feelsLike":31.86,"pressure":1015,"humidity":77,"windSpeed":6.51,"windDirection":152,"clouds":97,"windGust":6.6,"sunrise":1780367483,"sunset":1780411081},{"date":1780473600,"icon":"🌦","temp":27.44,"min":27.31,"max":27.79,"feelsLike":30.74,"pressure":1014,"humidity":80,"windSpeed":6.35,"windDirection":163,"clouds":93,"windGust":7.09,"sunrise":1780453892,"sunset":1780497491},{"date":1780560000,"icon":"🌦","temp":27.75,"min":27.46,"max":27.97,"feelsLike":31.08,"pressure":1013,"humidity":77,"windSpeed":6.55,"windDirection":159,"clouds":68,"windGust":6.47,"sunrise":1780540302,"sunset":1780583901},{"date":1780646400,"icon":"🌦","temp":28.11,"min":27.7,"max":28.11,"feelsLike":30.88,"pressure":1013,"humidity":70,"windSpeed":6.59,"windDirection":149,"clouds":82,"windGust":7.12,"sunrise":1780626712,"sunset":1780670311},{"date":1780732800,"icon":"🌦","temp":27.75,"min":27.71,"max":28,"feelsLike":30.31,"pressure":1014,"humidity":71,"windSpeed":7.56,"windDirection":173,"clouds":41,"windGust":7.71,"sunrise":1780713122,"sunset":1780756721},{"date":1780819200,"icon":"🌦","temp":28.14,"min":27.52,"max":28.14,"feelsLike":30.94,"pressure":1014,"humidity":70,"windSpeed":9.21,"windDirection":166,"clouds":100,"windGust":9.4,"sunrise":1780799533,"sunset":1780843132},{"date":1780905600,"icon":"🌦","temp":27.9,"min":27.66,"max":27.9,"feelsLike":31.56,"pressure":1014,"humidity":78,"windSpeed":8.69,"windDirection":168,"clouds":9,"windGust":9.12,"sunrise":1780885943,"sunset":1780929543},{"date":1780992000,"icon":"🌦","temp":27.81,"min":27.56,"max":27.81,"feelsLike":31.35,"pressure":1014,"humidity":78,"windSpeed":7.68,"windDirection":164,"clouds":8,"windGust":8.01,"sunrise":1780972354,"sunset":1781015954},{"date":1781078400,"icon":"🌦","temp":27.47,"min":27.47,"max":27.57,"feelsLike":30.81,"pressure":1013,"humidity":80,"windSpeed":7.22,"windDirection":162,"clouds":11,"windGust":7.38,"sunrise":1781058766,"sunset":1781102365},{"date":1781164800,"icon":"🌦","temp":27.61,"min":27.28,"max":27.61,"feelsLike":30.64,"pressure":1013,"humidity":76,"windSpeed":7.42,"windDirection":160,"clouds":26,"windGust":7.71,"sunrise":1781145177,"sunset":1781188777},{"date":1781251200,"icon":"☁️","temp":27.56,"min":26.93,"max":27.56,"feelsLike":30.18,"pressure":1014,"humidity":73,"windSpeed":7.58,"windDirection":186,"clouds":47,"windGust":7.97,"sunrise":1781231588,"sunset":1781275188},{"date":1781337600,"icon":"🌦","temp":27.46,"min":27.12,"max":27.53,"feelsLike":30.55,"pressure":1013,"humidity":78,"windSpeed":8.27,"windDirection":186,"clouds":76,"windGust":8.88,"sunrise":1781318000,"sunset":1781361600},{"date":1781424000,"icon":"🌦","temp":27.55,"min":27.19,"max":27.55,"feelsLike":30.88,"pressure":1012,"humidity":79,"windSpeed":7.77,"windDirection":172,"clouds":93,"windGust":8.58,"sunrise":1781404412,"sunset":1781448012},{"date":1781510400,"icon":"🌦","temp":27.54,"min":27.04,"max":27.62,"feelsLike":30.98,"pressure":1011,"humidity":80,"windSpeed":7.2,"windDirection":167,"clouds":25,"windGust":7.94,"sunrise":1781490824,"sunset":1781534424}]