[{"date":1688716800,"icon":"🌦","temp":25.95,"min":25.57,"max":26.21,"feelsLike":25.95,"pressure":1014,"humidity":80,"windSpeed":10.05,"windDirection":182,"clouds":97,"windGust":11.52,"sunrise":1688697474,"sunset":1688741073},{"date":1688803200,"icon":"🌦","temp":25.82,"min":25.62,"max":26.08,"feelsLike":26.47,"pressure":1015,"humidity":77,"windSpeed":9.75,"windDirection":188,"clouds":18,"windGust":10.61,"sunrise":1688783883,"sunset":1688827482},{"date":1688889600,"icon":"🌦","temp":26.06,"min":25.46,"max":26.47,"feelsLike":26.06,"pressure":1013,"humidity":82,"windSpeed":7.8,"windDirection":226,"clouds":51,"windGust":8.63,"sunrise":1688870292,"sunset":1688913891},{"date":1688976000,"icon":"🌦","temp":26.17,"min":25.95,"max":26.26,"feelsLike":26.17,"pressure":1012,"humidity":82,"windSpeed":7.64,"windDirection":165,"clouds":57,"windGust":8.32,"sunrise":1688956701,"sunset":1689000299},{"date":1689062400,"icon":"🌦","temp":26.24,"min":25.93,"max":26.24,"feelsLike":26.24,"pressure":1012,"humidity":82,"windSpeed":7.28,"windDirection":182,"clouds":44,"windGust":8.49,"sunrise":1689043109,"sunset":1689086708},{"date":1689148800,"icon":"🌦","temp":26.07,"min":25.84,"max":26.07,"feelsLike":26.07,"pressure":1013,"humidity":81,"windSpeed":8.6,"windDirection":193,"clouds":48,"windGust":9.69,"sunrise":1689129517,"sunset":1689173115},{"date":1689235200,"icon":"🌦","temp":25.8,"min":25.73,"max":25.89,"feelsLike":26.47,"pressure":1013,"humidity":78,"windSpeed":9.14,"windDirection":190,"clouds":58,"windGust":9.86,"sunrise":1689215925,"sunset":1689259523},{"date":1689321600,"icon":"🌦","temp":25.7,"min":25.58,"max":25.89,"feelsLike":26.44,"pressure":1013,"humidity":81,"windSpeed":8.84,"windDirection":189,"clouds":89,"windGust":9.88,"sunrise":1689302332,"sunset":1689345930},{"date":1689408000,"icon":"🌦","temp":25.53,"min":25.37,"max":25.79,"feelsLike":26.25,"pressure":1013,"humidity":81,"windSpeed":8.45,"windDirection":188,"clouds":89,"windGust":9.47,"sunrise":1689388739,"sunset":1689432336},{"date":1689494400,"icon":"🌦","temp":25.76,"min":25.14,"max":25.83,"feelsLike":26.43,"pressure":1014,"humidity":78,"windSpeed":8.16,"windDirection":171,"clouds":100,"windGust":9.17,"sunrise":1689475145,"sunset":1689518742},{"date":1689580800,"icon":"🌦","temp":25.85,"min":25.51,"max":25.89,"feelsLike":26.58,"pressure":1015,"humidity":80,"windSpeed":8.47,"windDirection":166,"clouds":51,"windGust":9.68,"sunrise":1689561551,"sunset":1689605148},{"date":1689667200,"icon":"🌦","temp":25.72,"min":25.26,"max":25.8,"feelsLike":26.44,"pressure":1015,"humidity":80,"windSpeed":8.46,"windDirection":168,"clouds":8,"windGust":9.61,"sunrise":1689647956,"sunset":1689691553},{"date":1689753600,"icon":"🌦","temp":25.72,"min":25.44,"max":25.77,"feelsLike":26.49,"pressure":1015,"humidity":82,"windSpeed":8.33,"windDirection":172,"clouds":36,"windGust":9.52,"sunrise":1689734361,"sunset":1689777957},{"date":1689840000,"icon":"🌦","temp":25.84,"min":25.57,"max":25.95,"feelsLike":26.65,"pressure":1015,"humidity":83,"windSpeed":8.56,"windDirection":178,"clouds":5,"windGust":9.67,"sunrise":1689820765,"sunset":1689864362},{"date":1689926400,"icon":"🌦","temp":26,"min":25.57,"max":26.1,"feelsLike":26,"pressure":1016,"humidity":83,"windSpeed":7.77,"windDirection":183,"clouds":65,"windGust":8.96,"sunrise":1689907169,"sunset":1689950765},{"date":1690012800,"icon":"🌦","temp":26.04,"min":25.7,"max":26.05,"feelsLike":26.04,"pressure":1015,"humidity":83,"windSpeed":8.55,"windDirection":157,"clouds":20,"windGust":10.05,"sunrise":1689993572,"sunset":1690037168}]