[{"date":1655107200,"icon":"🌦","temp":27.17,"min":26.88,"max":27.34,"feelsLike":30.23,"pressure":1012,"humidity":81,"windSpeed":9.89,"windDirection":212,"clouds":91,"windGust":11.17,"sunrise":1655087600,"sunset":1655131200},{"date":1655193600,"icon":"🌦","temp":27.09,"min":27.07,"max":27.34,"feelsLike":30.04,"pressure":1012,"humidity":81,"windSpeed":8.82,"windDirection":194,"clouds":95,"windGust":9.43,"sunrise":1655174012,"sunset":1655217612},{"date":1655280000,"icon":"🌦","temp":27.37,"min":26.93,"max":27.38,"feelsLike":30.58,"pressure":1011,"humidity":80,"windSpeed":7.66,"windDirection":174,"clouds":13,"windGust":8.59,"sunrise":1655260424,"sunset":1655304024},{"date":1655366400,"icon":"🌦","temp":27.08,"min":26.84,"max":27.25,"feelsLike":29.72,"pressure":1011,"humidity":78,"windSpeed":6.57,"windDirection":171,"clouds":85,"windGust":7.67,"sunrise":1655346836,"sunset":1655390436},{"date":1655452800,"icon":"🌦","temp":26.97,"min":26.91,"max":27.11,"feelsLike":29.67,"pressure":1011,"humidity":80,"windSpeed":8.28,"windDirection":182,"clouds":100,"windGust":9.45,"sunrise":1655433248,"sunset":1655476848},{"date":1655539200,"icon":"🌦","temp":27.03,"min":26.84,"max":27.07,"feelsLike":29.81,"pressure":1012,"humidity":80,"windSpeed":8.49,"windDirection":188,"clouds":95,"windGust":9.51,"sunrise":1655519660,"sunset":1655563261},{"date":1655625600,"icon":"🌦","temp":26.9,"min":26.65,"max":27.04,"feelsLike":29.52,"pressure":1011,"humidity":80,"windSpeed":8.75,"windDirection":197,"clouds":59,"windGust":9.65,"sunrise":1655606073,"sunset":1655649673},{"date":1655712000,"icon":"🌦","temp":27.03,"min":26.6,"max":27.04,"feelsLike":29.62,"pressure":1012,"humidity":78,"windSpeed":9.26,"windDirection":168,"clouds":38,"windGust":10.52,"sunrise":1655692485,"sunset":1655736085},{"date":1655798400,"icon":"🌦","temp":26.98,"min":26.33,"max":27.02,"feelsLike":29.51,"pressure":1011,"humidity":78,"windSpeed":9.55,"windDirection":185,"clouds":99,"windGust":10.78,"sunrise":1655778897,"sunset":1655822497},{"date":1655884800,"icon":"🌦","temp":26.78,"min":26.32,"max":26.84,"feelsLike":28.79,"pressure":1011,"humidity":74,"windSpeed":9.62,"windDirection":186,"clouds":100,"windGust":10.83,"sunrise":1655865309,"sunset":1655908910},{"date":1655971200,"icon":"🌦","temp":26.82,"min":26.54,"max":26.82,"feelsLike":29.43,"pressure":1010,"humidity":81,"windSpeed":9.19,"windDirection":205,"clouds":87,"windGust":10.29,"sunrise":1655951721,"sunset":1655995322},{"date":1656057600,"icon":"🌦","temp":26.49,"min":26,"max":26.49,"feelsLike":26.49,"pressure":1010,"humidity":83,"windSpeed":9.86,"windDirection":185,"clouds":99,"windGust":11.3,"sunrise":1656038133,"sunset":1656081734},{"date":1656144000,"icon":"🌦","temp":26.58,"min":26.25,"max":26.75,"feelsLike":26.58,"pressure":1010,"humidity":80,"windSpeed":10.22,"windDirection":185,"clouds":100,"windGust":11.53,"sunrise":1656124545,"sunset":1656168146},{"date":1656230400,"icon":"🌦","temp":26.78,"min":26.21,"max":26.79,"feelsLike":29.1,"pressure":1010,"humidity":78,"windSpeed":9.56,"windDirection":194,"clouds":96,"windGust":10.74,"sunrise":1656210957,"sunset":1656254558},{"date":1656316800,"icon":"🌦","temp":26.6,"min":25.96,"max":26.73,"feelsLike":26.6,"pressure":1010,"humidity":82,"windSpeed":8.97,"windDirection":200,"clouds":53,"windGust":10.34,"sunrise":1656297369,"sunset":1656340969},{"date":1656403200,"icon":"🌦","temp":26.38,"min":26.29,"max":26.57,"feelsLike":26.38,"pressure":1010,"humidity":80,"windSpeed":7.35,"windDirection":221,"clouds":87,"windGust":7.94,"sunrise":1656383781,"sunset":1656427381}]