[{"date":1656748800,"icon":"🌦","temp":25.3,"min":25.07,"max":25.35,"feelsLike":25.84,"pressure":1014,"humidity":75,"windSpeed":10.09,"windDirection":195,"clouds":47,"windGust":12.28,"sunrise":1656729426,"sunset":1656773025},{"date":1656835200,"icon":"🌦","temp":25.31,"min":25.07,"max":25.37,"feelsLike":26.04,"pressure":1013,"humidity":82,"windSpeed":10.9,"windDirection":194,"clouds":87,"windGust":12.94,"sunrise":1656815836,"sunset":1656859436},{"date":1656921600,"icon":"🌦","temp":25.28,"min":25.08,"max":25.3,"feelsLike":26,"pressure":1013,"humidity":82,"windSpeed":9.77,"windDirection":182,"clouds":96,"windGust":11.3,"sunrise":1656902247,"sunset":1656945846},{"date":1657008000,"icon":"🌦","temp":25.29,"min":25.06,"max":25.29,"feelsLike":26.07,"pressure":1012,"humidity":84,"windSpeed":9.48,"windDirection":191,"clouds":100,"windGust":11.21,"sunrise":1656988657,"sunset":1657032256},{"date":1657094400,"icon":"🌦","temp":25.24,"min":24.88,"max":25.24,"feelsLike":25.96,"pressure":1012,"humidity":82,"windSpeed":10.29,"windDirection":185,"clouds":11,"windGust":12.32,"sunrise":1657075067,"sunset":1657118666},{"date":1657180800,"icon":"🌦","temp":25.07,"min":24.86,"max":25.13,"feelsLike":25.75,"pressure":1013,"humidity":81,"windSpeed":10.23,"windDirection":187,"clouds":100,"windGust":11.98,"sunrise":1657161476,"sunset":1657205075},{"date":1657267200,"icon":"🌦","temp":25.1,"min":24.68,"max":25.1,"feelsLike":25.75,"pressure":1013,"humidity":80,"windSpeed":10.42,"windDirection":192,"clouds":64,"windGust":11.95,"sunrise":1657247886,"sunset":1657291484},{"date":1657353600,"icon":"🌦","temp":25.06,"min":24.83,"max":25.06,"feelsLike":25.71,"pressure":1013,"humidity":80,"windSpeed":10.74,"windDirection":198,"clouds":38,"windGust":12.88,"sunrise":1657334295,"sunset":1657377893},{"date":1657440000,"icon":"🌦","temp":24.99,"min":24.76,"max":24.99,"feelsLike":25.61,"pressure":1012,"humidity":79,"windSpeed":11.1,"windDirection":197,"clouds":8,"windGust":13.04,"sunrise":1657420703,"sunset":1657464302},{"date":1657526400,"icon":"🌦","temp":25.04,"min":24.79,"max":25.04,"feelsLike":25.79,"pressure":1013,"humidity":84,"windSpeed":10.26,"windDirection":211,"clouds":65,"windGust":12.8,"sunrise":1657507111,"sunset":1657550710},{"date":1657612800,"icon":"🌦","temp":25.19,"min":24.89,"max":25.19,"feelsLike":26.06,"pressure":1012,"humidity":88,"windSpeed":10.37,"windDirection":212,"clouds":15,"windGust":12.84,"sunrise":1657593519,"sunset":1657637117},{"date":1657699200,"icon":"🌦","temp":25.32,"min":25.02,"max":25.4,"feelsLike":26.21,"pressure":1012,"humidity":88,"windSpeed":9.22,"windDirection":205,"clouds":93,"windGust":11.75,"sunrise":1657679927,"sunset":1657723524},{"date":1657785600,"icon":"🌦","temp":25.29,"min":24.97,"max":25.29,"feelsLike":26.17,"pressure":1012,"humidity":88,"windSpeed":10.6,"windDirection":188,"clouds":95,"windGust":14.21,"sunrise":1657766334,"sunset":1657809931},{"date":1657872000,"icon":"🌦","temp":25.24,"min":24.98,"max":25.24,"feelsLike":26.12,"pressure":1013,"humidity":88,"windSpeed":10.22,"windDirection":189,"clouds":92,"windGust":13.8,"sunrise":1657852740,"sunset":1657896338},{"date":1657958400,"icon":"🌦","temp":25.08,"min":24.84,"max":25.08,"feelsLike":25.97,"pressure":1012,"humidity":89,"windSpeed":9.77,"windDirection":199,"clouds":84,"windGust":12.51,"sunrise":1657939146,"sunset":1657982744},{"date":1658044800,"icon":"🌦","temp":25.16,"min":24.88,"max":25.21,"feelsLike":26,"pressure":1012,"humidity":87,"windSpeed":8.97,"windDirection":199,"clouds":21,"windGust":11.1,"sunrise":1658025552,"sunset":1658069149}]